artemis_mcp/__init__.py
artemis_mcp/__main__.py
artemis_mcp/server.py
mseep_artemis_mcp-0.1.10.dist-info/METADATA
mseep_artemis_mcp-0.1.10.dist-info/WHEEL
mseep_artemis_mcp-0.1.10.dist-info/entry_points.txt
mseep_artemis_mcp-0.1.10.dist-info/top_level.txt
mseep_artemis_mcp-0.1.10.dist-info/RECORD
