Metadata-Version: 2.4
Name: mseep-artemis-mcp
Version: 0.1.10
Summary: Artemis MCP Server to Connect with Artemis API and Create ART Formulas
Author-email: mseep <support@skydeck.ai>
Project-URL: Homepage, https://artemis.xyz
Project-URL: Repository, https://github.com/Artemis-xyz/artemis-mcp
Project-URL: Documentation, https://github.com/Artemis-xyz/artemis-mcp#readme
Project-URL: Bug Tracker, https://github.com/Artemis-xyz/artemis-mcp/issues
Keywords: artemis,mcp,crypto,stablecoins,digital finance
Requires-Python: >=3.10
Requires-Dist: build>=1.2.2.post1
Requires-Dist: httpx>=0.28.1
Requires-Dist: mcp[cli]>=1.3.0
Requires-Dist: twine>=6.1.0
